{"paths": {"admin/js/vendor/select2/i18n/pt.js": "admin/js/vendor/select2/i18n/pt.33b4a3b44d43.js", "admin/js/vendor/select2/i18n/hsb.js": "admin/js/vendor/select2/i18n/hsb.fa3b55265efe.js", "admin/js/vendor/select2/i18n/vi.js": "admin/js/vendor/select2/i18n/vi.097a5b75b3e1.js", "admin/js/vendor/select2/i18n/lv.js": "admin/js/vendor/select2/i18n/lv.08e62128eac1.js", "admin/js/vendor/select2/i18n/gl.js": "admin/js/vendor/select2/i18n/gl.d99b1fedaa86.js", "admin/js/vendor/select2/i18n/pl.js": "admin/js/vendor/select2/i18n/pl.6031b4f16452.js", "admin/js/vendor/select2/i18n/el.js": "admin/js/vendor/select2/i18n/el.27097f071856.js", "admin/js/vendor/select2/i18n/dsb.js": "admin/js/vendor/select2/i18n/dsb.56372c92d2f1.js", "admin/js/vendor/select2/i18n/et.js": "admin/js/vendor/select2/i18n/et.2b96fd98289d.js", "admin/js/vendor/select2/i18n/is.js": "admin/js/vendor/select2/i18n/is.3ddd9a6a97e9.js", "admin/js/vendor/select2/i18n/sl.js": "admin/js/vendor/select2/i18n/sl.131a78bc0752.js", "admin/js/vendor/select2/i18n/ko.js": "admin/js/vendor/select2/i18n/ko.e7be6c20e673.js", "admin/js/vendor/select2/i18n/hr.js": "admin/js/vendor/select2/i18n/hr.a2b092cc1147.js", "admin/js/vendor/select2/i18n/ms.js": "admin/js/vendor/select2/i18n/ms.4ba82c9a51ce.js", "admin/js/vendor/select2/i18n/fi.js": "admin/js/vendor/select2/i18n/fi.614ec42aa9ba.js", "admin/js/vendor/select2/i18n/th.js": "admin/js/vendor/select2/i18n/th.f38c20b0221b.js", "admin/js/vendor/select2/i18n/ru.js": "admin/js/vendor/select2/i18n/ru.934aa95f5b5f.js", "admin/js/vendor/select2/i18n/eu.js": "admin/js/vendor/select2/i18n/eu.adfe5c97b72c.js", "admin/js/vendor/select2/i18n/mk.js": "admin/js/vendor/select2/i18n/mk.dabbb9087130.js", "admin/js/vendor/select2/i18n/sq.js": "admin/js/vendor/select2/i18n/sq.5636b60d29c9.js", "admin/js/vendor/select2/i18n/ja.js": "admin/js/vendor/select2/i18n/ja.170ae885d74f.js", "admin/js/vendor/select2/i18n/ka.js": "admin/js/vendor/select2/i18n/ka.2083264a54f0.js", "admin/js/vendor/select2/i18n/he.js": "admin/js/vendor/select2/i18n/he.e420ff6cd3ed.js", "admin/js/vendor/select2/i18n/bg.js": "admin/js/vendor/select2/i18n/bg.39b8be30d4f0.js", "admin/js/vendor/select2/i18n/hy.js": "admin/js/vendor/select2/i18n/hy.c7babaeef5a6.js", "admin/js/vendor/select2/i18n/sr-Cyrl.js": "admin/js/vendor/select2/i18n/sr-Cyrl.f254bb8c4c7c.js", "admin/js/vendor/select2/i18n/ne.js": "admin/js/vendor/select2/i18n/ne.3d79fd3f08db.js", "admin/js/vendor/select2/i18n/af.js": "admin/js/vendor/select2/i18n/af.4f6fcd73488c.js", "admin/js/vendor/select2/i18n/id.js": "admin/js/vendor/select2/i18n/id.04debded514d.js", "admin/js/vendor/select2/i18n/az.js": "admin/js/vendor/select2/i18n/az.270c257daf81.js", "admin/js/vendor/select2/i18n/ca.js": "admin/js/vendor/select2/i18n/ca.a166b745933a.js", "admin/js/vendor/select2/i18n/nb.js": "admin/js/vendor/select2/i18n/nb.da2fce143f27.js", "admin/js/vendor/select2/i18n/zh-CN.js": "admin/js/vendor/select2/i18n/zh-CN.2cff662ec5f9.js", "admin/js/vendor/select2/i18n/zh-TW.js": "admin/js/vendor/select2/i18n/zh-TW.04554a227c2b.js", "admin/js/vendor/select2/i18n/pt-BR.js": "admin/js/vendor/select2/i18n/pt-BR.e1b294433e7f.js", "admin/js/vendor/select2/i18n/da.js": "admin/js/vendor/select2/i18n/da.766346afe4dd.js", "admin/js/vendor/select2/i18n/fa.js": "admin/js/vendor/select2/i18n/fa.3b5bd1961cfd.js", "admin/js/vendor/select2/i18n/de.js": "admin/js/vendor/select2/i18n/de.8a1c222b0204.js", "admin/js/vendor/select2/i18n/en.js": "admin/js/vendor/select2/i18n/en.cf932ba09a98.js", "admin/js/vendor/select2/i18n/bs.js": "admin/js/vendor/select2/i18n/bs.91624382358e.js", "admin/js/vendor/select2/i18n/tk.js": "admin/js/vendor/select2/i18n/tk.7c572a68c78f.js", "admin/js/vendor/select2/i18n/sv.js": "admin/js/vendor/select2/i18n/sv.7a9c2f71e777.js", "admin/js/vendor/select2/i18n/hi.js": "admin/js/vendor/select2/i18n/hi.70640d41628f.js", "admin/js/vendor/select2/i18n/uk.js": "admin/js/vendor/select2/i18n/uk.8cede7f4803c.js", "admin/js/vendor/select2/i18n/cs.js": "admin/js/vendor/select2/i18n/cs.4f43e8e7d33a.js", "admin/js/vendor/select2/i18n/km.js": "admin/js/vendor/select2/i18n/km.c23089cb06ca.js", "admin/js/vendor/select2/i18n/fr.js": "admin/js/vendor/select2/i18n/fr.05e0542fcfe6.js", "admin/js/vendor/select2/i18n/nl.js": "admin/js/vendor/select2/i18n/nl.997868a37ed8.js", "admin/js/vendor/select2/i18n/sr.js": "admin/js/vendor/select2/i18n/sr.5ed85a48f483.js", "admin/js/vendor/select2/i18n/hu.js": "admin/js/vendor/select2/i18n/hu.6ec6039cb8a3.js", "admin/js/vendor/select2/i18n/lt.js": "admin/js/vendor/select2/i18n/lt.23c7ce903300.js", "admin/js/vendor/select2/i18n/ar.js": "admin/js/vendor/select2/i18n/ar.65aa8e36bf5d.js", "admin/js/vendor/select2/i18n/sk.js": "admin/js/vendor/select2/i18n/sk.33d02cef8d11.js", "admin/js/vendor/select2/i18n/it.js": "admin/js/vendor/select2/i18n/it.be4fe8d365b5.js", "admin/js/vendor/select2/i18n/es.js": "admin/js/vendor/select2/i18n/es.66dbc2652fb1.js", "admin/js/vendor/select2/i18n/bn.js": "admin/js/vendor/select2/i18n/bn.6d42b4dd5665.js", "admin/js/vendor/select2/i18n/ro.js": "admin/js/vendor/select2/i18n/ro.f75cb460ec3b.js", "admin/js/vendor/select2/i18n/ps.js": "admin/js/vendor/select2/i18n/ps.38dfa47af9e0.js", "admin/js/vendor/select2/i18n/tr.js": "admin/js/vendor/select2/i18n/tr.b5a0643d1545.js", "admin/css/vendor/select2/select2.min.css": "admin/css/vendor/select2/select2.min.9f54e6414f87.css", "admin/css/vendor/select2/LICENSE-SELECT2.md": "admin/css/vendor/select2/LICENSE-SELECT2.f94142512c91.md", "admin/css/vendor/select2/select2.css": "admin/css/vendor/select2/select2.a2194c262648.css", "admin/js/vendor/jquery/jquery.min.js": "admin/js/vendor/jquery/jquery.min.dc5e7f18c8d3.js", "admin/js/vendor/jquery/LICENSE.txt": "admin/js/vendor/jquery/LICENSE.75308107741f.txt", "admin/js/vendor/jquery/jquery.js": "admin/js/vendor/jquery/jquery.23c7c5d2d131.js", "admin/js/vendor/xregexp/xregexp.min.js": "admin/js/vendor/xregexp/xregexp.min.b0439563a5d3.js", "admin/js/vendor/xregexp/xregexp.js": "admin/js/vendor/xregexp/xregexp.efda034b9537.js", "admin/js/vendor/xregexp/LICENSE.txt": "admin/js/vendor/xregexp/LICENSE.bf79e414957a.txt", "admin/js/vendor/select2/LICENSE.md": "admin/js/vendor/select2/LICENSE.f94142512c91.md", "admin/js/vendor/select2/select2.full.min.js": "admin/js/vendor/select2/select2.full.min.fcd7500d8e13.js", "admin/js/vendor/select2/select2.full.js": "admin/js/vendor/select2/select2.full.c2afdeda3058.js", "admin/js/admin/RelatedObjectLookups.js": "admin/js/admin/RelatedObjectLookups.b4d76b6aaf0b.js", "admin/js/admin/DateTimeShortcuts.js": "admin/js/admin/DateTimeShortcuts.5548f99471bf.js", "admin/img/gis/move_vertex_on.svg": "admin/img/gis/move_vertex_on.0047eba25b67.svg", "admin/img/gis/move_vertex_off.svg": "admin/img/gis/move_vertex_off.7a23bf31ef8a.svg", "css/images/ui-icons_d8e7f3_256x240.png": "css/images/ui-icons_d8e7f3_256x240.d41d8cd98f00.png", "css/images/ui-icons_cd0a0a_256x240.png": "css/images/ui-icons_cd0a0a_256x240.d41d8cd98f00.png", "css/images/ui-icons_6da8d5_256x240.png": "css/images/ui-icons_6da8d5_256x240.d41d8cd98f00.png", "css/images/ui-icons_2e83ff_256x240.png": "css/images/ui-icons_2e83ff_256x240.d41d8cd98f00.png", "css/images/ui-bg_inset-hard_100_f5f8f9_1x100.png": "css/images/ui-bg_inset-hard_100_f5f8f9_1x100.d41d8cd98f00.png", "css/images/ui-icons_217bc0_256x240.png": "css/images/ui-icons_217bc0_256x240.d41d8cd98f00.png", "css/images/ui-bg_glass_85_dfeffc_1x400.png": "css/images/ui-bg_glass_85_dfeffc_1x400.d41d8cd98f00.png", "css/images/ui-bg_glass_95_fef1ec_1x400.png": "css/images/ui-bg_glass_95_fef1ec_1x400.d41d8cd98f00.png", "css/images/ui-bg_glass_75_d0e5f5_1x400.png": "css/images/ui-bg_glass_75_d0e5f5_1x400.d41d8cd98f00.png", "css/images/ui-icons_469bdd_256x240.png": "css/images/ui-icons_469bdd_256x240.d41d8cd98f00.png", "css/images/ui-bg_gloss-wave_55_5c9ccc_500x100.png": "css/images/ui-bg_gloss-wave_55_5c9ccc_500x100.d41d8cd98f00.png", "css/images/ui-bg_inset-hard_100_fcfdfd_1x100.png": "css/images/ui-bg_inset-hard_100_fcfdfd_1x100.d41d8cd98f00.png", "css/images/ui-icons_f9bd01_256x240.png": "css/images/ui-icons_f9bd01_256x240.d41d8cd98f00.png", "css/fonts/flexslider-icon.woff": "css/fonts/flexslider-icon.d41d8cd98f00.woff", "css/fonts/flexslider-icon.ttf": "css/fonts/flexslider-icon.d41d8cd98f00.ttf", "css/fonts/flexslider-icon.eot": "css/fonts/flexslider-icon.d41d8cd98f00.eot", "css/fonts/flexslider-icon.svg": "css/fonts/flexslider-icon.d41d8cd98f00.svg", "img/app-download-img/app-download-img-shape.png": "img/app-download-img/app-download-img-shape.d41d8cd98f00.png", "admin/css/widgets.css": "admin/css/widgets.694d845b2cb1.css", "admin/css/login.css": "admin/css/login.c35adf41bb6e.css", "admin/css/dashboard.css": "admin/css/dashboard.be83f13e4369.css", "admin/css/nav_sidebar.css": "admin/css/nav_sidebar.0fd434145f4d.css", "admin/css/responsive.css": "admin/css/responsive.b128bdf0edef.css", "admin/css/autocomplete.css": "admin/css/autocomplete.4a81fc4242d0.css", "admin/css/responsive_rtl.css": "admin/css/responsive_rtl.e13ae754cceb.css", "admin/css/forms.css": "admin/css/forms.1d89ec6432f5.css", "admin/css/fonts.css": "admin/css/fonts.168bab448fee.css", "admin/css/rtl.css": "admin/css/rtl.4bc23eb90919.css", "admin/css/base.css": "admin/css/base.1f418065fc2c.css", "admin/css/changelists.css": "admin/css/changelists.c70d77c47e69.css", "admin/js/urlify.js": "admin/js/urlify.25cc3eac8123.js", "admin/js/core.js": "admin/js/core.ccd84108ec57.js", "admin/js/collapse.js": "admin/js/collapse.f84e7410290f.js", "admin/js/actions.js": "admin/js/actions.d1ca6151ab51.js", "admin/js/prepopulate.js": "admin/js/prepopulate.bd2361dfd64d.js", "admin/js/cancel.js": "admin/js/cancel.ecc4c5ca7b32.js", "admin/js/nav_sidebar.js": "admin/js/nav_sidebar.7605597ddf52.js", "admin/js/autocomplete.js": "admin/js/autocomplete.b6b77d0e5906.js", "admin/js/inlines.js": "admin/js/inlines.7596b7fd289e.js", "admin/js/change_form.js": "admin/js/change_form.9d8ca4f96b75.js", "admin/js/SelectFilter2.js": "admin/js/SelectFilter2.d250dcb52a9a.js", "admin/js/jquery.init.js": "admin/js/jquery.init.b7781a0897fc.js", "admin/js/popup_response.js": "admin/js/popup_response.c6cc78ea5551.js", "admin/js/SelectBox.js": "admin/js/SelectBox.8161741c7647.js", "admin/js/calendar.js": "admin/js/calendar.f8a5d055eb33.js", "admin/js/prepopulate_init.js": "admin/js/prepopulate_init.e056047b7a7e.js", "admin/img/search.svg": "admin/img/search.7cf54ff789c6.svg", "admin/img/icon-calendar.svg": "admin/img/icon-calendar.ac7aea671bea.svg", "admin/img/icon-clock.svg": "admin/img/icon-clock.e1d4dfac3f2b.svg", "admin/img/icon-no.svg": "admin/img/icon-no.439e821418cd.svg", "admin/img/tooltag-add.svg": "admin/img/tooltag-add.e59d620a9742.svg", "admin/img/inline-delete.svg": "admin/img/inline-delete.fec1b761f254.svg", "admin/img/LICENSE": "admin/img/LICENSE.2c54f4e1ca1c", "admin/img/icon-changelink.svg": "admin/img/icon-changelink.18d2fd706348.svg", "admin/img/icon-unknown.svg": "admin/img/icon-unknown.a18cb4398978.svg", "admin/img/sorting-icons.svg": "admin/img/sorting-icons.3a097b59f104.svg", "admin/img/icon-viewlink.svg": "admin/img/icon-viewlink.41eb31f7826e.svg", "admin/img/icon-yes.svg": "admin/img/icon-yes.d2f9f035226a.svg", "admin/img/icon-addlink.svg": "admin/img/icon-addlink.d519b3bab011.svg", "admin/img/icon-unknown-alt.svg": "admin/img/icon-unknown-alt.81536e128bb6.svg", "admin/img/icon-deletelink.svg": "admin/img/icon-deletelink.564ef9dc3854.svg", "admin/img/README.txt": "admin/img/README.a70711a38d87.txt", "admin/img/selector-icons.svg": "admin/img/selector-icons.b4555096cea2.svg", "admin/img/calendar-icons.svg": "admin/img/calendar-icons.39b290681a8b.svg", "admin/img/tooltag-arrowright.svg": "admin/img/tooltag-arrowright.bbfb788a849e.svg", "admin/img/icon-alert.svg": "admin/img/icon-alert.034cc7d8a67f.svg", "admin/fonts/Roboto-Light-webfont.woff": "admin/fonts/Roboto-Light-webfont.c73eb1ceba33.woff", "admin/fonts/Roboto-Bold-webfont.woff": "admin/fonts/Roboto-Bold-webfont.50d75e48e0a3.woff", "admin/fonts/Roboto-Regular-webfont.woff": "admin/fonts/Roboto-Regular-webfont.35b07eb2f871.woff", "admin/fonts/README.txt": "admin/fonts/README.ab99e6b541ea.txt", "admin/fonts/LICENSE.txt": "admin/fonts/LICENSE.d273d63619c9.txt", "css/bootstrap.min.css": "css/bootstrap.min.f54e35c93504.css", "css/theme-default.css": "css/theme-default.b9a7a62fe129.css", "css/jquery-ui.min.css": "css/jquery-ui.min.67344340c402.css", "css/animate.min.css": "css/animate.min.386be9480d96.css", "css/font-awesome-all.min.css": "css/font-awesome-all.min.cecc36036ef7.css", "css/flex-slider.css": "css/flex-slider.199599b0e984.css", "css/swiper-slider.min.css": "css/swiper-slider.min.af10a943d3cd.css", "css/video-popup.min.css": "css/video-popup.min.2c828506f8e2.css", "css/aos.min.css": "css/aos.min.847da8fca806.css", "css/select2-min.css": "css/select2-min.e71c39430469.css", "js/swiper-slider.min.js": "js/swiper-slider.min.bb71422af3dd.js", "js/jquery-ui.min.js": "js/jquery-ui.min.1b72df4bf433.js", "js/easing.min.js": "js/easing.min.260a6ac923f8.js", "js/select2-js.min.js": "js/select2-js.min.7c98b05dd4f3.js", "js/flex-slider.js": "js/flex-slider.5b54121569f6.js", "js/waypoints.min.js": "js/waypoints.min.4fe14337a62d.js", "js/ckeditor.min.js": "js/ckeditor.min.0390cbe1848e.js", "js/video-popup.min.js": "js/video-popup.min.63d86a19ecd7.js", "js/jquery.min.js": "js/jquery.min.0732e3eabbf8.js", "js/swiper-bundle.min.js.map": "js/swiper-bundle.min.js.d41d8cd98f00.map", "js/bootstrap.min.js": "js/bootstrap.min.a08792f518b5.js", "js/aos.min.js": "js/aos.min.a01f9089e830.js", "js/jquery-migrate.js": "js/jquery-migrate.84cf3d32b3d7.js", "js/active.js": "js/active.828e06af023c.js", "js/ckeditor.js.map": "js/ckeditor.js.d41d8cd98f00.map", "js/bootstrap.min.js.map": "js/bootstrap.min.js.d41d8cd98f00.map", "js/jquery.counterup.min.js": "js/jquery.counterup.min.4f0e0b047f2e.js", "img/funfact-icon2.svg": "img/funfact-icon2.f318516fb8e2.svg", "img/pd-icon-1.svg": "img/pd-icon-1.2f62e0f4fac4.svg", "img/anim-shape-3.svg": "img/anim-shape-3.073056e8643b.svg", "img/anim-shape-2.svg": "img/anim-shape-2.43f044d09a25.svg", "img/footer-bg.jpg": "img/footer-bg.54c05d04117f.jpg", "img/bg-shape-one.svg": "img/bg-shape-one.0c69af927aec.svg", "img/funfact-icon3.svg": "img/funfact-icon3.961ca5b015c3.svg", "img/footer-bg.png": "img/footer-bg.54b951c08921.png", "img/agent-bg-2.jpg": "img/agent-bg-2.35ef3db13771.jpg", "img/funfact-icon1.svg": "img/funfact-icon1.6363d0665fde.svg", "img/property-bg.svg": "img/property-bg.9adceddd521a.svg", "img/pd-icon-2.svg": "img/pd-icon-2.8f303ccdedd6.svg", "img/anim-shape-1.svg": "img/anim-shape-1.789d29b83f51.svg", "img/finance-icon.svg": "img/finance-icon.9bc6902905e6.svg", "img/pd-icon-3.svg": "img/pd-icon-3.5cc644502094.svg", "img/feature-card-icon4.svg": "img/feature-card-icon4.b18546c0efee.svg", "img/bath-icon.svg": "img/bath-icon.1955b3aee323.svg", "img/room-icon2.svg": "img/room-icon2.f58d145c8285.svg", "img/agent-email.svg": "img/agent-email.964943e671a6.svg", "img/date-icon.svg": "img/date-icon.b84dda6b0801.svg", "img/funfact-icon4.svg": "img/funfact-icon4.2cad6556e223.svg", "img/anim-shape-5.svg": "img/anim-shape-5.f8207904d2e8.svg", "img/anim-shape-4.svg": "img/anim-shape-4.4ecf75b48449.svg", "img/property-sale.png": "img/property-sale.e6404d0de05d.png", "img/pd-icon-6.svg": "img/pd-icon-6.f399f4dacfa0.svg", "img/vector.svg": "img/vector.67300f63a1fc.svg", "img/feature-card-icon1.svg": "img/feature-card-icon1.596c9e051a1b.svg", "img/feature-card-icon3.svg": "img/feature-card-icon3.d03ddee3400b.svg", "img/footer-phone.svg": "img/footer-phone.535116fe7164.svg", "img/plus-icon.svg": "img/plus-icon.d67fee162421.svg", "img/map.svg": "img/map.35951c5315ea.svg", "img/phone-icon.svg": "img/phone-icon.917313d59f26.svg", "img/pd-icon-4.svg": "img/pd-icon-4.c146622420f5.svg", "img/anim-shape-6.svg": "img/anim-shape-6.dbc8ce4f61db.svg", "img/anim-shape-7.svg": "img/anim-shape-7.cdc677fa65c4.svg", "img/pd-icon-5.svg": "img/pd-icon-5.90392050ebe0.svg", "img/bg-shape-four.svg": "img/bg-shape-four.be9c3a93cae1.svg", "img/feature-card-icon2.svg": "img/feature-card-icon2.22f19b193397.svg", "img/logo-footer.png": "img/logo-footer.4d05c5863110.png", "img/location-icon.svg": "img/location-icon.37d62ddac7cc.svg", "img/shape-2.svg": "img/shape-2.f451b19396cc.svg", "img/user-icon.svg": "img/user-icon.ce841b3cecfb.svg", "img/arrow-icon.svg": "img/arrow-icon.9a23eb04608b.svg", "img/size-icon2.svg": "img/size-icon2.4ffde0f8144d.svg", "img/shape-3.svg": "img/shape-3.bb4d9be3b6fb.svg", "img/Map.png": "img/Map.2e51be35ca7b.png", "img/vector-left.svg": "img/vector-left.8b4bdd9d6359.svg", "img/email-icon.svg": "img/email-icon.337459ec1bc5.svg", "img/footer-location.png": "img/footer-location.121d582e1833.png", "img/anim-shape-10.svg": "img/anim-shape-10.7c9d8866b2f1.svg", "img/founder.jpeg": "img/founder.636757a5cfae.jpeg", "img/property-rent.png": "img/property-rent.28eb9c8537b8.png", "img/icon.svg": "img/icon.1468702ce475.svg", "img/footer-message.png": "img/footer-message.7ad0bc79797f.png", "img/locaiton-icon.svg": "img/locaiton-icon.974b148af9c4.svg", "img/anim-shape-11.svg": "img/anim-shape-11.39d48bfc5268.svg", "img/video-popup-overlay.svg": "img/video-popup-overlay.9e2d493b3ab9.svg", "img/hero-shape-group-2.svg": "img/hero-shape-group-2.6a53143acf4e.svg", "img/background.jpg": "img/background.c911a411f0bb.jpg", "img/shape.png": "img/shape.a73d4f748644.png", "img/loader.svg": "img/loader.b26666e0ee51.svg", "img/size-icon.svg": "img/size-icon.b2cce7f46f8a.svg", "img/bg-black-shape.jpg": "img/bg-black-shape.cfee8feb62cd.jpg", "img/welcome-bg.svg": "img/welcome-bg.32bd1235d6da.svg", "img/count-icon1.svg": "img/count-icon1.5007c4c82aa2.svg", "img/logo-white.png": "img/logo-white.4d05c5863110.png", "img/hero-shape-group2.svg": "img/hero-shape-group2.b4bbc7e4c8fa.svg", "img/welcome-logo.png": "img/welcome-logo.21cd85d3e4a8.png", "img/favicon.png": "img/favicon.0242e5b676ac.png", "img/count-icon2.svg": "img/count-icon2.902361cf144e.svg", "img/features-list-bg.svg": "img/features-list-bg.cdaf770013b0.svg", "img/vector-right.svg": "img/vector-right.62d56343c82c.svg", "img/hand-icon.svg": "img/hand-icon.75fdc7b73851.svg", "img/logo.jpg": "img/logo.aef97456c515.jpg", "img/download-vector.svg": "img/download-vector.a764c0028ba5.svg", "img/agent-phone.svg": "img/agent-phone.a5b5963336d8.svg", "img/bg-pattern1.png": "img/bg-pattern1.eeddea6261dc.png", "img/google.svg": "img/google.c69b85fc8c79.svg", "img/wide-house-icon.svg": "img/wide-house-icon.8ac508edd630.svg", "img/support-icon-white.svg": "img/support-icon-white.322bc3eee328.svg", "img/support-icon.svg": "img/support-icon.ce3ff0f5c0c0.svg", "img/location-icon2.svg": "img/location-icon2.09f99f993ae1.svg", "img/delete-icon.svg": "img/delete-icon.bae7cea6fd33.svg", "img/bath-icon2.svg": "img/bath-icon2.496fb3a372ad.svg", "img/upload-file-2.svg": "img/upload-file-2.fe95f444015a.svg", "img/bg-shape-three.svg": "img/bg-shape-three.d33b99a3c1e1.svg", "img/room-icon.svg": "img/room-icon.d7ea8dae13d7.svg", "img/property-single-bg.svg": "img/property-single-bg.abbf06b800fb.svg", "img/hero-shape-group.svg": "img/hero-shape-group.fb160fef1d19.svg", "img/map-icon.svg": "img/map-icon.3702e9f91821.svg", "img/dash-icon6.svg": "img/dash-icon6.c267af66f3e9.svg", "img/locations-icon.svg": "img/locations-icon.97cb160bcd53.svg", "img/bg-shape-two.svg": "img/bg-shape-two.d87fff1573e1.svg", "img/floor-plane-img.png": "img/floor-plane-img.e0801721a444.png", "img/dash-icon5.svg": "img/dash-icon5.1e429ca9035d.svg", "img/anim-shape-9.svg": "img/anim-shape-9.3d684700a70a.svg", "img/comment.svg": "img/comment.fa3b6bb88413.svg", "img/calendar.svg": "img/calendar.09417e299701.svg", "img/anim-shape-8.svg": "img/anim-shape-8.f6c78e8a45e6.svg", "img/download-vector.png": "img/download-vector.deeaf9d59a98.png", "img/bread-overlay.jpg": "img/bread-overlay.d212fe288129.jpg", "img/dash-icon4.svg": "img/dash-icon4.0938cb619b51.svg", "img/section-shape.svg": "img/section-shape.f8a90e5aaedc.svg", "img/userplaceholder.png": "img/userplaceholder.a71fe96bbcb6.png", "img/founderBG.jpg": "img/founderBG.e110fb72d121.jpg", "img/bg-shape-five.svg": "img/bg-shape-five.f56f5277dba0.svg", "img/upload-file.svg": "img/upload-file.79534ad649d1.svg", "img/dash-icon1.svg": "img/dash-icon1.7fab978b0c39.svg", "img/dash-icon3.svg": "img/dash-icon3.231039830250.svg", "img/agent-location.svg": "img/agent-location.7270740c7900.svg", "img/property-ag-bg.svg": "img/property-ag-bg.8df94df0eb85.svg", "img/dash-icon2.svg": "img/dash-icon2.f646a47d12c9.svg", "webfonts/fa-solid-900.ttf": "webfonts/fa-solid-900.b9625119ce43.ttf", "webfonts/fa-regular-400.svg": "webfonts/fa-regular-400.c5d109be8edd.svg", "webfonts/fa-regular-400.woff2": "webfonts/fa-regular-400.b91d376b8d76.woff2", "webfonts/fa-solid-900.eot": "webfonts/fa-solid-900.0c6bfc668a72.eot", "webfonts/fa-brands-400.svg": "webfonts/fa-brands-400.1d5619cd8043.svg", "webfonts/fa-regular-400.woff": "webfonts/fa-regular-400.d1d7e3b4c219.woff", "webfonts/fa-brands-400.eot": "webfonts/fa-brands-400.592643a83b85.eot", "webfonts/fa-solid-900.svg": "webfonts/fa-solid-900.37bc7099f6f1.svg", "webfonts/fa-v4compatibility.ttf": "webfonts/fa-v4compatibility.d41d8cd98f00.ttf", "webfonts/fa-solid-900.woff": "webfonts/fa-solid-900.d745348d289b.woff", "webfonts/fa-regular-400.ttf": "webfonts/fa-regular-400.766913e6c008.ttf", "webfonts/fa-v4compatibility.woff2": "webfonts/fa-v4compatibility.d41d8cd98f00.woff2", "webfonts/fa-solid-900.woff2": "webfonts/fa-solid-900.d824df7eb2e2.woff2", "webfonts/fa-brands-400.woff2": "webfonts/fa-brands-400.ed311c7a0ade.woff2", "webfonts/fa-brands-400.woff": "webfonts/fa-brands-400.1a575a4138e5.woff", "webfonts/fa-brands-400.ttf": "webfonts/fa-brands-400.513aa607d398.ttf", "webfonts/fa-regular-400.eot": "webfonts/fa-regular-400.b0e2db3b634d.eot", "style.css": "style.085529cd7be4.css"}, "version": "1.0"}